LICENSE.txt
README.md
setup.cfg
setup.py
techx_pdf2text/Pdf2Text.py
techx_pdf2text/__init__.py
techx_pdf2text/get_link.py
techx_pdf2text/post_process.py
techx_pdf2text/text_clean.py
techx_pdf2text/utils.py
techx_pdf2text.egg-info/PKG-INFO
techx_pdf2text.egg-info/SOURCES.txt
techx_pdf2text.egg-info/dependency_links.txt
techx_pdf2text.egg-info/requires.txt
techx_pdf2text.egg-info/top_level.txt